azure/storage/blob/changefeed/__init__.py
azure/storage/blob/changefeed/_change_feed_client.py
azure/storage/blob/changefeed/_models.py
azure/storage/blob/changefeed/_version.py
azure/storage/blob/changefeed/py.typed
azure_storage_blob_changefeed-12.0.0b5.dist-info/LICENSE
azure_storage_blob_changefeed-12.0.0b5.dist-info/METADATA
azure_storage_blob_changefeed-12.0.0b5.dist-info/WHEEL
azure_storage_blob_changefeed-12.0.0b5.dist-info/top_level.txt
azure_storage_blob_changefeed-12.0.0b5.dist-info/RECORD
