Metadata-Version: 2.1
Name: azure-storage-blob-changefeed
Version: 12.0.0b5
Summary: Microsoft Azure Storage Blob ChangeFeed Client Library for Python
Home-page: https://github.com/Azure/azure-sdk-for-python/tree/main/sdk/storage/azure-storage-blob-changefeed
Author: Microsoft Corporation
Author-email: ascl@microsoft.com
License: MIT License
Keywords: azure,azure sdk
Classifier: Development Status :: 4 - Beta
Classifier: Programming Language :: Python
Classifier: Programming Language :: Python :: 3 :: Only
Classifier: Programming Language :: Python :: 3
Classifier: Programming Language :: Python :: 3.8
Classifier: Programming Language :: Python :: 3.9
Classifier: Programming Language :: Python :: 3.10
Classifier: Programming Language :: Python :: 3.11
Classifier: Programming Language :: Python :: 3.12
Classifier: License :: OSI Approved :: MIT License
Requires-Python: >=3.8
License-File: LICENSE
Requires-Dist: azure-storage-blob <13.0.0,>=12.19.1
